pycnp-0.1.4.dist-info/RECORD
pycnp-0.1.4.dist-info/WHEEL
pycnp-0.1.4.dist-info/METADATA
pycnp-0.1.4.dist-info/licenses/LICENSE
pycnp/params.py
pycnp/MemeticSearch.py
pycnp/constants.py
pycnp/__init__.py
pycnp/visualization.py
pycnp/Model.py
pycnp/Result.py
pycnp/pycnp_docs.h
pycnp/ProgressPrinter.py
pycnp/exceptions.py
pycnp/_pycnp.cpython-39-darwin.so
pycnp/Statistics.py
pycnp/_pycnp.pyi
pycnp/read.py
pycnp/validation.py
pycnp/stop/NoImprovement.py
pycnp/stop/__init__.py
pycnp/stop/StoppingCriterion.py
pycnp/stop/MaxIterations.py
pycnp/stop/MaxRuntime.py
pycnp/crossover/double_backbone_based_crossover.py
pycnp/crossover/__init__.py
pycnp/crossover/_crossover.cpython-39-darwin.so
pycnp/crossover/inherit_repair_recombination.py
pycnp/crossover/_crossover.pyi
pycnp/crossover/crossover_docs.h
pycnp/crossover/reduce_solve_combine.py
pycnp/cpp/ProblemData.cpp
pycnp/cpp/Population.h
pycnp/cpp/SearchResult.h
pycnp/cpp/RandomNumberGenerator.h
pycnp/cpp/ProblemData.h
pycnp/cpp/pybind.cpp
pycnp/cpp/Population.cpp
pycnp/cpp/Graph/Types.h
pycnp/cpp/Graph/CNP_Graph.cpp
pycnp/cpp/Graph/Graph.cpp
pycnp/cpp/Graph/DCNP_Graph.cpp
pycnp/cpp/Graph/Graph.h
pycnp/cpp/Graph/CNP_Graph.h
pycnp/cpp/Graph/DCNP_Graph.h
pycnp/cpp/search/CHNSStrategy.cpp
pycnp/cpp/search/DLASStrategy.h
pycnp/cpp/search/SearchStrategy.h
pycnp/cpp/search/BCLSStrategy.h
pycnp/cpp/search/BCLSStrategy.cpp
pycnp/cpp/search/CBNSStrategy.cpp
pycnp/cpp/search/DLASStrategy.cpp
pycnp/cpp/search/CBNSStrategy.h
pycnp/cpp/search/Search.cpp
pycnp/cpp/search/SearchUtils.h
pycnp/cpp/search/Search.h
pycnp/cpp/search/CHNSStrategy.h
pycnp/cpp/crossover/inherit_repair_recombination.h
pycnp/cpp/crossover/pybind.cpp
pycnp/cpp/crossover/doubleBackboneBasedCrossover.h
pycnp/cpp/crossover/doubleBackboneBasedCrossover.cpp
pycnp/cpp/crossover/reduceSolveCombine.h
pycnp/cpp/crossover/reduceSolveCombine.cpp
pycnp/cpp/crossover/inherit_repair_recombination.cpp
