Metadata-Version: 2.4
Name: pycnp
Version: 0.1.4
Summary: A high-performance Python solver for Critical Node Problems
License-Expression: MIT
License-File: LICENSE
Keywords: graph,optimization,critical-node-problem,algorithms,metaheuristic
Author: Bo Xue
Author-email: x3219658574@126.com
Requires-Python: >=3.9
Classifier: Intended Audience :: Developers
Classifier: Intended Audience :: Science/Research
Classifier: Development Status :: 4 - Beta
Classifier: Topic :: Software Development
Classifier: Topic :: Scientific/Engineering
Classifier: Topic :: Scientific/Engineering :: Mathematics
Classifier: Programming Language :: Python :: 3
Classifier: Programming Language :: Python :: 3.9
Classifier: Programming Language :: Python :: 3.10
Classifier: Programming Language :: Python :: 3.11
Classifier: Programming Language :: Python :: 3.12
Classifier: Programming Language :: Python :: 3.13
Classifier: Programming Language :: C++
Provides-Extra: dev
Provides-Extra: docs
Provides-Extra: examples
Provides-Extra: visualization
Requires-Dist: matplotlib (>=3.5.0) ; extra == "examples"
Requires-Dist: mypy (>=1.0.0) ; extra == "dev"
Requires-Dist: myst-parser (>=2.0.0) ; extra == "docs"
Requires-Dist: nbsphinx (>=0.9.0) ; extra == "docs"
Requires-Dist: numpy (>=1.19.0) ; python_version < "3.12"
Requires-Dist: numpy (>=1.26.0) ; python_version >= "3.12"
Requires-Dist: numpydoc (>=1.5.0) ; extra == "docs"
Requires-Dist: pre-commit (>=3.0.0) ; extra == "dev"
Requires-Dist: psutil (>=5.8.0) ; extra == "examples"
Requires-Dist: pytest (>=7.0.0) ; extra == "dev"
Requires-Dist: pytest-cov (>=4.0.0) ; extra == "dev"
Requires-Dist: pytest-sugar (>=1.0.0) ; extra == "dev"
Requires-Dist: pytest-xdist (>=3.6.1) ; extra == "dev"
Requires-Dist: pyvis (>=0.3.0) ; extra == "visualization"
Requires-Dist: ruff (>=0.1.0) ; extra == "dev"
Requires-Dist: sphinx (>=6.0.0) ; extra == "docs"
Requires-Dist: sphinx-autobuild (>=2021.3.14) ; extra == "docs"
Requires-Dist: sphinx-immaterial (>=0.11.0) ; extra == "docs"
Requires-Dist: sphinx-rtd-theme (>=1.2.0) ; extra == "docs"
Project-URL: Documentation, https://xuebo100.github.io/PyCNP
Project-URL: Homepage, https://github.com/xuebo100/PyCNP
Project-URL: issues, https://github.com/xuebo100/PyCNP/issues
Project-URL: source, https://github.com/xuebo100/PyCNP
